django_rest_framework_camel_case/__init__.py
django_rest_framework_camel_case/parser.py
django_rest_framework_camel_case/render.py
django_rest_framework_camel_case/settings.py
django_rest_framework_camel_case/util.py
django_rest_framework_camel_case-2.0.0.dist-info/AUTHORS.rst
django_rest_framework_camel_case-2.0.0.dist-info/LICENSE
django_rest_framework_camel_case-2.0.0.dist-info/METADATA
django_rest_framework_camel_case-2.0.0.dist-info/WHEEL
django_rest_framework_camel_case-2.0.0.dist-info/top_level.txt
django_rest_framework_camel_case-2.0.0.dist-info/RECORD
