Metadata-Version: 2.1
Name: django-rest-framework-camel-case
Version: 2.0.0
Summary: Camel case JSON support for Django REST framework.
Home-page: https://github.com/Envive/djangorestframework-camel-case
Author: Pocheng, playma
Author-email: pcghuang@gmail.com, scott820914@gmail.com
License: BSD
Keywords: django_rest_framework_camel_case
Platform: UNKNOWN
Classifier: Development Status :: 2 - Pre-Alpha
Classifier: Intended Audience :: Developers
Classifier: License :: OSI Approved :: BSD License
Classifier: Natural Language :: English
Classifier: Programming Language :: Python :: 2
Classifier: Programming Language :: Python :: 2.6
Classifier: Programming Language :: Python :: 2.7
Classifier: Programming Language :: Python :: 3
Classifier: Programming Language :: Python :: 3.3
